Metadata-Version: 2.1
Name: taimos.cdk-construct-gitlab-variable
Version: 1.0.1
Summary: An AWS CDK Construct that creates GITLAB CI/CD variables from SecretsManager Secrets
Home-page: https://github.com/taimos/cdk-construct-gitlab-variable
Author: Thorsten Hoeger<thorsten.hoeger@taimos.de>
License: Apache-2.0
Project-URL: Source, https://github.com/taimos/cdk-construct-gitlab-variable
Platform: UNKNOWN
Classifier: Intended Audience :: Developers
Classifier: Operating System :: OS Independent
Classifier: Programming Language :: JavaScript
Classifier: Programming Language :: Python :: 3 :: Only
Classifier: Programming Language :: Python :: 3.6
Classifier: Programming Language :: Python :: 3.7
Classifier: Programming Language :: Python :: 3.8
Classifier: Typing :: Typed
Classifier: License :: OSI Approved
Requires-Python: >=3.6
